seven_cmstar_platform/__init__.py
seven_cmstar_platform/platform_helper.py
seven_cmstar_platform/handlers/__init__.py
seven_cmstar_platform/handlers/app_helper.py
seven_cmstar_platform/handlers/doll_app_base.py
seven_cmstar_platform/handlers/doll_app_helper.py
seven_cmstar_platform/handlers/qqmini_helper.py
seven_cmstar_platform/handlers/wxmini_helper.py
seven_cmstar_platform/libs/__init__.py
seven_cmstar_platform/libs/baidu_aip_censor.py
seven_cmstar_platform/libs/sms_helper.py
seven_cmstar_platform/models/__init__.py
seven_cmstar_platform/models/action_log_model.py
seven_cmstar_platform/models/asset_base_model.py
seven_cmstar_platform/models/cache_model.py
seven_cmstar_platform/models/enum.py
seven_cmstar_platform/models/invite_model.py
seven_cmstar_platform/models/seven_model.py
seven_cmstar_platform/models/user_base_model.py
seven_cmstar_platform/models/db_models/__init__.py
seven_cmstar_platform/models/db_models/ezgame/__init__.py
seven_cmstar_platform/models/db_models/ezgame/ezgame_user_action_log_model.py
seven_cmstar_platform/models/db_models/ezgame/ezgame_user_statistics_log_model.py
seven_cmstar_platform/models/db_models/platform/__init__.py
seven_cmstar_platform/models/db_models/platform/platform_asset_inventory_model.py
seven_cmstar_platform/models/db_models/platform/platform_asset_log_model.py
seven_cmstar_platform/models/db_models/platform/platform_asset_only_model.py
seven_cmstar_platform/models/db_models/platform/platform_asset_warn_notice_model.py
seven_cmstar_platform/models/db_models/platform/platform_base_info_model.py
seven_cmstar_platform/models/db_models/platform/platform_dict_info_model.py
seven_cmstar_platform/models/db_models/platform/platform_doll_info_model.py
seven_cmstar_platform/models/db_models/platform/platform_search_statistics_log_model.py
seven_cmstar_platform/models/db_models/platform/platform_user_address_model.py
seven_cmstar_platform/models/db_models/platform/platform_user_asset_model.py
seven_cmstar_platform-1.0.2.19.dist-info/METADATA
seven_cmstar_platform-1.0.2.19.dist-info/WHEEL
seven_cmstar_platform-1.0.2.19.dist-info/top_level.txt
seven_cmstar_platform-1.0.2.19.dist-info/RECORD
