Metadata-Version: 2.1
Name: seven-cmstar-platform
Version: 1.0.2.19
Summary: seven cmstar platform
Home-page: UNKNOWN
Author: seven
Author-email: tech@gao7.com
License: MIT
Platform: UNKNOWN
Classifier: Topic :: Software Development :: Libraries :: Python Modules
Classifier: Programming Language :: Python
Classifier: Programming Language :: Python :: 3.4
Classifier: Programming Language :: Python :: 3.5
Classifier: Programming Language :: Python :: 3.6
Classifier: Programming Language :: Python :: 3.7
Classifier: Programming Language :: Python :: 3.8
Classifier: Programming Language :: Python :: 3.9
Requires-Python: ~=3.4
Requires-Dist: seven-framework (>=1.0.131.4)
Requires-Dist: PyJWT (==1.7.1)
Requires-Dist: bintrees (==2.1.0)
Requires-Dist: bce-python-sdk (==0.8.61)
Requires-Dist: baidu-aip-sdk (==4.15.14)
Requires-Dist: chardet (==4.0.0)
